[
 {
  "table":"SRVDSRC",
  "data":
  [
   {
    "SRVDNAME":"ZETR_DDL_D_EDOC_NUMBER_RANGES",
    "VERSION":"A",
    "CHANGED_BY":"SAP_CUSTOMER",
    "CHANGED_ON":"2024-12-11",
    "CHANGED_AT":"09:03:01",
    "DT_UUID":"CB92D17136801EEFADF3D71C6AA642D9",
    "SOURCE_ORIGIN":"0",
    "SRVD_SOURCE_TYPE":"S",
    "ABAP_LANGUAGE_VERSION":"5"
   }
  ]
 },
 {
  "table":"SRVDSRCT",
  "data":
  [
   {
    "SRVDNAME":"ZETR_DDL_D_EDOC_NUMBER_RANGES",
    "VERSION":"A",
    "LANGUAGE":"E",
    "DESCRIPTION":"eDocuments Number Ranges"
   }
  ]
 },
 {
  "table":"SRVDSRC_SRC",
  "data":
  [
   {
    "SRVDNAME":"ZETR_DDL_D_EDOC_NUMBER_RANGES",
    "VERSION":"A",
    "SOURCE":"@EndUserText.label: 'eDocuments Number Ranges'\r\ndefine service ZETR_DDL_D_EDOC_NUMBER_RANGES {\r\n  expose zetr_ddl_p_edoc_number_ranges as NumberRanges;\r\n  expose zetr_ddl_p_edoc_number_status as NumberStatuses;\r\n}"
   }
  ]
 },
 {
  "table":"SRVD_RT_ANNOS",
  "data":
  [
   {
    "SRVDNAME":"ZETR_DDL_D_EDOC_NUMBER_RANGES",
    "NAME":"ENDUSERTEXT.LABEL",
    "VALUE":"'eDocuments Number Ranges'"
   }
  ]
 },
 {
  "table":"SRVD_RT_ANNOS_T",
  "data":
  [
   {
    "SRVDNAME":"ZETR_DDL_D_EDOC_NUMBER_RANGES",
    "LANGUAGE":"E",
    "NAME":"ENDUSERTEXT.LABEL",
    "TEXT":"eDocuments Number Ranges"
   }
  ]
 },
 {
  "table":"SRVD_RT_ENTITIES",
  "data":
  [
   {
    "SRVDNAME":"ZETR_DDL_D_EDOC_NUMBER_RANGES",
    "SERVICE":"ZETR_DDL_D_EDOC_NUMBER_RANGES",
    "EXPOSED_ARTIFACT":"ZETR_DDL_P_EDOC_NUMBER_RANGES",
    "EXPOSED_ARTIFACT_TYPE":"E",
    "EXPOSED_ALIAS":"NUMBERRANGES",
    "EXPOSED_ALIAS_RAW":"NumberRanges",
    "INCL_SERVICE":""
   },
   {
    "SRVDNAME":"ZETR_DDL_D_EDOC_NUMBER_RANGES",
    "SERVICE":"ZETR_DDL_D_EDOC_NUMBER_RANGES",
    "EXPOSED_ARTIFACT":"ZETR_DDL_P_EDOC_NUMBER_STATUS",
    "EXPOSED_ARTIFACT_TYPE":"E",
    "EXPOSED_ALIAS":"NUMBERSTATUSES",
    "EXPOSED_ALIAS_RAW":"NumberStatuses",
    "INCL_SERVICE":""
   }
  ]
 },
 {
  "table":"SRVD_RT_HEADER",
  "data":
  [
   {
    "SRVDNAME":"ZETR_DDL_D_EDOC_NUMBER_RANGES",
    "SERVICE":"ZETR_DDL_D_EDOC_NUMBER_RANGES",
    "SERVICE_RAW":"ZETR_DDL_D_EDOC_NUMBER_RANGES",
    "SOURCE_TYPE":"S",
    "DT_UUID":"CB92D17136801EEFADF3D71C6AA642D9",
    "RT_HASH":"F6D3916507E500D19A8F2057A34DDC465638500D",
    "GEN_VERSION":"0"
   }
  ]
 },
 {
  "table":"TADIR",
  "data":
  [
   {
    "PGMID":"R3TR",
    "OBJECT":"SRVD",
    "OBJ_NAME":"ZETR_DDL_D_EDOC_NUMBER_RANGES",
    "KORRNUM":"",
    "SRCSYSTEM":"...",
    "AUTHOR":"SAP_CUSTOMER",
    "SRCDEP":"",
    "DEVCLASS":"ZETR0",
    "GENFLAG":"",
    "EDTFLAG":"",
    "CPROJECT":" L",
    "MASTERLANG":"E",
    "VERSID":"",
    "PAKNOCHECK":"",
    "OBJSTABLTY":"",
    "COMPONENT":"",
    "CRELEASE":"",
    "DELFLAG":"",
    "TRANSLTTXT":"",
    "CREATED_ON":"2024-12-11",
    "CHECK_DATE":"2024-12-11",
    "CHECK_CFG":""
   }
  ]
 }
]